{"layers": [{"ddd": 0, "ty": 4, "sr": 1, "ip": 0, "op": 60, "st": 0, "ks": {"s": {"k": [100, 100], "a": 0}, "o": {"k": 100, "a": 0}}, "ao": 0, "bm": 0, "shapes": [{"ty": "gr", "it": [{"ty": "sh", "d": 1, "ks": {"k": {"c": true, "i": [[0, 0], [0, 0], [0, 0], [0, 0], [0, 0]], "o": [[0, 0], [0, 0], [0, 0], [0, 0], [0, 0]], "v": [[34.688, 20.604], [28.125, 20.604], [28.125, 26.229], [34.688, 26.229], [34.688, 20.604]]}, "a": 0}}, {"ty": "st", "lc": 2, "lj": 2, "ml": 0, "o": {"k": 100, "a": 0}, "w": {"k": 1.875, "a": 0}, "c": {"k": [0.298, 0.141, 0.114, 1], "a": 0}}, {"ty": "fl", "o": {"k": 100, "a": 0}, "c": {"k": [0.008, 0.918, 0.902, 1], "a": 0}}, {"ty": "tr", "s": {"k": [100, 100], "a": 0}, "o": {"k": 100, "a": 0}}]}, {"ty": "gr", "it": [{"ty": "sh", "d": 1, "ks": {"k": {"c": false, "i": [[0, 0], [0, 0]], "o": [[0, 0], [0, 0]], "v": [[10.521, 6.153], [13.986, 9.617]]}, "a": 0}}, {"ty": "st", "lc": 2, "lj": 2, "ml": 0, "o": {"k": 100, "a": 0}, "w": {"k": 1.875, "a": 0}, "c": {"k": [0.298, 0.141, 0.114, 1], "a": 0}}, {"ty": "tr", "s": {"k": [100, 100], "a": 0}, "o": {"k": 100, "a": 0}}]}, {"ty": "gr", "it": [{"ty": "sh", "d": 1, "ks": {"k": {"c": false, "i": [[0, 0], [0, 0]], "o": [[0, 0], [0, 0]], "v": [[13.986, 6.153], [10.521, 9.617]]}, "a": 0}}, {"ty": "st", "lc": 2, "lj": 2, "ml": 0, "o": {"k": 100, "a": 0}, "w": {"k": 1.875, "a": 0}, "c": {"k": [0.298, 0.141, 0.114, 1], "a": 0}}, {"ty": "tr", "s": {"k": [100, 100], "a": 0}, "o": {"k": 100, "a": 0}}]}, {"ty": "gr", "it": [{"ty": "sh", "d": 1, "ks": {"k": {"c": true, "i": [[0, 0], [0, 0], [0, 0], [0, 0], [0, 0]], "o": [[0, 0], [0, 0], [0, 0], [0, 0], [0, 0]], "v": [[33.75, 4.666], [29.062, 4.666], [29.062, 9.354], [33.75, 9.354], [33.75, 4.666]]}, "a": 0}}, {"ty": "st", "lc": 2, "lj": 2, "ml": 0, "o": {"k": 100, "a": 0}, "w": {"k": 1.875, "a": 0}, "c": {"k": [0.298, 0.141, 0.114, 1], "a": 0}}, {"ty": "fl", "o": {"k": 100, "a": 0}, "c": {"k": [0.902, 0.388, 0.325, 1], "a": 0}}, {"ty": "tr", "s": {"k": [100, 100], "a": 0}, "o": {"k": 100, "a": 0}}]}, {"ty": "gr", "it": [{"ty": "sh", "d": 1, "ks": {"k": {"c": false, "i": [[0, 0], [0, 0]], "o": [[0, 0], [0, 0]], "v": [[15, 50.643], [47.812, 50.643]]}, "a": 0}}, {"ty": "st", "lc": 2, "lj": 2, "ml": 0, "o": {"k": 100, "a": 0}, "w": {"k": 1.875, "a": 0}, "c": {"k": [0.298, 0.141, 0.114, 1], "a": 0}}, {"ty": "tr", "s": {"k": [100, 100], "a": 0}, "o": {"k": 100, "a": 0}}]}, {"ty": "gr", "it": [{"ty": "sh", "d": 1, "ks": {"k": {"c": false, "i": [[0, 0], [0, 0]], "o": [[0, 0], [0, 0]], "v": [[42.188, 45.994], [42.188, 55.291]]}, "a": 0}}, {"ty": "st", "lc": 2, "lj": 2, "ml": 0, "o": {"k": 100, "a": 0}, "w": {"k": 1.875, "a": 0}, "c": {"k": [0.298, 0.141, 0.114, 1], "a": 0}}, {"ty": "tr", "s": {"k": [100, 100], "a": 0}, "o": {"k": 100, "a": 0}}]}, {"ty": "gr", "it": [{"ty": "sh", "d": 1, "ks": {"k": {"c": false, "i": [[0, 0], [0, 0]], "o": [[0, 0], [0, 0]], "v": [[38.438, 45.994], [38.438, 55.291]]}, "a": 0}}, {"ty": "st", "lc": 2, "lj": 2, "ml": 0, "o": {"k": 100, "a": 0}, "w": {"k": 1.875, "a": 0}, "c": {"k": [0.298, 0.141, 0.114, 1], "a": 0}}, {"ty": "tr", "s": {"k": [100, 100], "a": 0}, "o": {"k": 100, "a": 0}}]}, {"ty": "gr", "it": [{"ty": "sh", "d": 1, "ks": {"k": {"c": true, "i": [[0, 0], [0, 0], [0, 0], [0, 0], [0, 0]], "o": [[0, 0], [0, 0], [0, 0], [0, 0], [0, 0]], "v": [[35.625, 9.354], [27.188, 9.354], [27.188, 12.219], [35.625, 12.219], [35.625, 9.354]]}, "a": 0}}, {"ty": "st", "lc": 2, "lj": 2, "ml": 0, "o": {"k": 100, "a": 0}, "w": {"k": 1.875, "a": 0}, "c": {"k": [0.298, 0.141, 0.114, 1], "a": 0}}, {"ty": "fl", "o": {"k": 100, "a": 0}, "c": {"k": [0.42, 0.31, 0.357, 1], "a": 0}}, {"ty": "tr", "s": {"k": [100, 100], "a": 0}, "o": {"k": 100, "a": 0}}]}, {"ty": "gr", "it": [{"ty": "sh", "d": 1, "ks": {"k": {"c": true, "i": [[0, 0], [0, 0], [10.312, 2.108], [-11.689, 1.084], [-3.636, -0.337], [0, 0], [0, 0]], "o": [[0, 0], [0, 0], [0, 0], [3.636, -0.337], [11.689, 1.084], [-10.312, 2.108], [0, 0]], "v": [[34.844, 12.219], [27.968, 12.219], [12.5, 17.488], [25.941, 20.418], [36.872, 20.418], [50.313, 17.488], [34.844, 12.219]]}, "a": 0}}, {"ty": "st", "lc": 2, "lj": 2, "ml": 0, "o": {"k": 100, "a": 0}, "w": {"k": 1.875, "a": 0}, "c": {"k": [0.298, 0.141, 0.114, 1], "a": 0}}, {"ty": "fl", "o": {"k": 100, "a": 0}, "c": {"k": [0.902, 0.388, 0.325, 1], "a": 0}}, {"ty": "tr", "s": {"k": [100, 100], "a": 0}, "o": {"k": 100, "a": 0}}]}, {"ty": "gr", "it": [{"ty": "sh", "d": 1, "ks": {"k": {"c": true, "i": [[0, 0], [0, 0], [0, 0], [0, 0], [0, 0]], "o": [[0, 0], [0, 0], [0, 0], [0, 0], [0, 0]], "v": [[44.062, 20.604], [18.75, 20.604], [18.75, 26.229], [44.062, 26.229], [44.062, 20.604]]}, "a": 0}}, {"ty": "st", "lc": 2, "lj": 2, "ml": 0, "o": {"k": 100, "a": 0}, "w": {"k": 1.875, "a": 0}, "c": {"k": [0.298, 0.141, 0.114, 1], "a": 0}}, {"ty": "fl", "o": {"k": 100, "a": 0}, "c": {"k": [0.957, 0.682, 0.671, 1], "a": 0}}, {"ty": "tr", "s": {"k": [100, 100], "a": 0}, "o": {"k": 100, "a": 0}}]}, {"ty": "gr", "it": [{"ty": "sh", "d": 1, "ks": {"k": {"c": true, "i": [[0, 0], [0, 0], [0, 0], [0, 0], [0, 0]], "o": [[0, 0], [0, 0], [0, 0], [0, 0], [0, 0]], "v": [[47.812, 26.229], [15.938, 26.229], [15.938, 29.041], [47.812, 29.041], [47.812, 26.229]]}, "a": 0}}, {"ty": "st", "lc": 2, "lj": 2, "ml": 0, "o": {"k": 100, "a": 0}, "w": {"k": 1.875, "a": 0}, "c": {"k": [0.298, 0.141, 0.114, 1], "a": 0}}, {"ty": "fl", "o": {"k": 100, "a": 0}, "c": {"k": [0.42, 0.31, 0.357, 1], "a": 0}}, {"ty": "tr", "s": {"k": [100, 100], "a": 0}, "o": {"k": 100, "a": 0}}]}, {"ty": "gr", "it": [{"ty": "sh", "d": 1, "ks": {"k": {"c": true, "i": [[0, 0], [0, 0], [4.819, -0.971], [-17.001, 3.58], [0.254, 2.765]], "o": [[0, 0], [-1.066, 3.235], [17.001, 3.58], [-5.478, -1.185], [0, 0]], "v": [[48.021, 29.041], [15.365, 29.041], [5.625, 34.794], [57.188, 34.794], [48.021, 29.041]]}, "a": 0}}, {"ty": "st", "lc": 2, "lj": 2, "ml": 0, "o": {"k": 100, "a": 0}, "w": {"k": 1.875, "a": 0}, "c": {"k": [0.298, 0.141, 0.114, 1], "a": 0}}, {"ty": "fl", "o": {"k": 100, "a": 0}, "c": {"k": [0.902, 0.388, 0.325, 1], "a": 0}}, {"ty": "tr", "s": {"k": [100, 100], "a": 0}, "o": {"k": 100, "a": 0}}]}, {"ty": "gr", "it": [{"ty": "sh", "d": 1, "ks": {"k": {"c": false, "i": [[0, 0], [0, 0]], "o": [[0, 0], [0, 0]], "v": [[9.063, 45.994], [54.322, 45.994]]}, "a": 0}}, {"ty": "st", "lc": 2, "lj": 2, "ml": 0, "o": {"k": 100, "a": 0}, "w": {"k": 1.875, "a": 0}, "c": {"k": [0.298, 0.141, 0.114, 1], "a": 0}}, {"ty": "tr", "s": {"k": [100, 100], "a": 0}, "o": {"k": 100, "a": 0}}]}, {"ty": "gr", "it": [{"ty": "sh", "d": 1, "ks": {"k": {"c": false, "i": [[0, 0], [0, 0], [0, 0], [0, 0]], "o": [[0, 0], [0, 0], [0, 0], [0, 0]], "v": [[44.062, 36.831], [44.062, 45.916], [36.562, 45.916], [36.562, 37.479]]}, "a": 0}}, {"ty": "st", "lc": 2, "lj": 2, "ml": 0, "o": {"k": 100, "a": 0}, "w": {"k": 1.875, "a": 0}, "c": {"k": [0.298, 0.141, 0.114, 1], "a": 0}}, {"ty": "tr", "s": {"k": [100, 100], "a": 0}, "o": {"k": 100, "a": 0}}]}, {"ty": "gr", "it": [{"ty": "sh", "d": 1, "ks": {"k": {"c": false, "i": [[0, 0], [0, 0], [0, 0], [0, 0]], "o": [[0, 0], [0, 0], [0, 0], [0, 0]], "v": [[44.062, 36.831], [44.062, 45.916], [36.562, 45.916], [36.562, 37.479]]}, "a": 0}}, {"ty": "fl", "o": {"k": 100, "a": 0}, "c": {"k": [0.008, 0.918, 0.902, 1], "a": 0}}, {"ty": "tr", "s": {"k": [100, 100], "a": 0}, "o": {"k": 100, "a": 0}}]}, {"ty": "gr", "it": [{"ty": "sh", "d": 1, "ks": {"k": {"c": false, "i": [[0, 0], [0, 0], [0, 0], [0, 0]], "o": [[0, 0], [0, 0], [0, 0], [0, 0]], "v": [[18.75, 36.831], [18.75, 45.916], [26.25, 45.916], [26.25, 37.479]]}, "a": 0}}, {"ty": "st", "lc": 2, "lj": 2, "ml": 0, "o": {"k": 100, "a": 0}, "w": {"k": 1.875, "a": 0}, "c": {"k": [0.298, 0.141, 0.114, 1], "a": 0}}, {"ty": "tr", "s": {"k": [100, 100], "a": 0}, "o": {"k": 100, "a": 0}}]}, {"ty": "gr", "it": [{"ty": "sh", "d": 1, "ks": {"k": {"c": false, "i": [[0, 0], [0, 0], [0, 0], [0, 0]], "o": [[0, 0], [0, 0], [0, 0], [0, 0]], "v": [[18.75, 36.831], [18.75, 45.916], [26.25, 45.916], [26.25, 37.479]]}, "a": 0}}, {"ty": "fl", "o": {"k": 100, "a": 0}, "c": {"k": [0.008, 0.918, 0.902, 1], "a": 0}}, {"ty": "tr", "s": {"k": [100, 100], "a": 0}, "o": {"k": 100, "a": 0}}]}, {"ty": "gr", "it": [{"ty": "sh", "d": 1, "ks": {"k": {"c": false, "i": [[0, 0], [0, 0], [0, 0], [0, 0]], "o": [[0, 0], [0, 0], [0, 0], [0, 0]], "v": [[47.812, 36.977], [47.812, 45.916], [15, 45.916], [15, 36.391]]}, "a": 0}}, {"ty": "st", "lc": 2, "lj": 2, "ml": 0, "o": {"k": 100, "a": 0}, "w": {"k": 1.875, "a": 0}, "c": {"k": [0.298, 0.141, 0.114, 1], "a": 0}}, {"ty": "tr", "s": {"k": [100, 100], "a": 0}, "o": {"k": 100, "a": 0}}]}, {"ty": "gr", "it": [{"ty": "sh", "d": 1, "ks": {"k": {"c": false, "i": [[0, 0], [0, 0], [0, 0], [0, 0]], "o": [[0, 0], [0, 0], [0, 0], [0, 0]], "v": [[47.812, 36.977], [47.812, 45.916], [15, 45.916], [15, 36.391]]}, "a": 0}}, {"ty": "fl", "o": {"k": 100, "a": 0}, "c": {"k": [0.957, 0.682, 0.671, 1], "a": 0}}, {"ty": "tr", "s": {"k": [100, 100], "a": 0}, "o": {"k": 100, "a": 0}}]}, {"ty": "gr", "it": [{"ty": "sh", "d": 1, "ks": {"k": {"c": true, "i": [[0, 0], [0, 0], [0, 0], [0, 0], [0, 0]], "o": [[0, 0], [0, 0], [0, 0], [0, 0], [0, 0]], "v": [[47.812, 45.994], [15, 45.994], [15, 55.291], [47.812, 55.291], [47.812, 45.994]]}, "a": 0}}, {"ty": "st", "lc": 2, "lj": 2, "ml": 0, "o": {"k": 100, "a": 0}, "w": {"k": 1.875, "a": 0}, "c": {"k": [0.298, 0.141, 0.114, 1], "a": 0}}, {"ty": "fl", "o": {"k": 100, "a": 0}, "c": {"k": [0.749, 0.494, 0.408, 1], "a": 0}}, {"ty": "tr", "s": {"k": [100, 100], "a": 0}, "o": {"k": 100, "a": 0}}]}, {"ty": "gr", "it": [{"ty": "sh", "d": 1, "ks": {"k": {"c": false, "i": [[0, 0], [-0.703, 0.703], [-0.995, 0], [0, 0], [-0.703, -0.703], [0, -0.994]], "o": [[0, -0.994], [0.703, -0.703], [0, 0], [0.995, 0], [0.703, 0.703], [0, 0]], "v": [[5.625, 59.041], [6.723, 56.389], [9.375, 55.291], [53.438, 55.291], [56.089, 56.389], [57.188, 59.041]]}, "a": 0}}, {"ty": "st", "lc": 2, "lj": 2, "ml": 0, "o": {"k": 100, "a": 0}, "w": {"k": 1.875, "a": 0}, "c": {"k": [0.298, 0.141, 0.114, 1], "a": 0}}, {"ty": "tr", "s": {"k": [100, 100], "a": 0}, "o": {"k": 100, "a": 0}}]}, {"ty": "gr", "it": [{"ty": "sh", "d": 1, "ks": {"k": {"c": false, "i": [[0, 0], [-0.703, 0.703], [-0.995, 0], [0, 0], [-0.703, -0.703], [0, -0.994]], "o": [[0, -0.994], [0.703, -0.703], [0, 0], [0.995, 0], [0.703, 0.703], [0, 0]], "v": [[5.625, 59.041], [6.723, 56.389], [9.375, 55.291], [53.438, 55.291], [56.089, 56.389], [57.188, 59.041]]}, "a": 0}}, {"ty": "fl", "o": {"k": 100, "a": 0}, "c": {"k": [0.71, 0.631, 0.612, 1], "a": 0}}, {"ty": "tr", "s": {"k": [100, 100], "a": 0}, "o": {"k": 100, "a": 0}}]}, {"ty": "gr", "it": [{"ty": "sh", "d": 1, "ks": {"k": {"c": true, "i": [[0, 0], [0, 0.518], [0.518, 0], [0, -0.518], [-0.518, 0]], "o": [[0.518, 0], [0, -0.518], [-0.518, 0], [0, 0.518], [0, 0]], "v": [[6.562, 29.041], [7.5, 28.104], [6.562, 27.166], [5.625, 28.104], [6.562, 29.041]]}, "a": 0}}, {"ty": "fl", "o": {"k": 100, "a": 0}, "c": {"k": [0.298, 0.141, 0.114, 1], "a": 0}}, {"ty": "tr", "s": {"k": [100, 100], "a": 0}, "o": {"k": 100, "a": 0}}]}, {"ty": "gr", "it": [{"ty": "sh", "d": 1, "ks": {"k": {"c": true, "i": [[0, 0], [0, 0.518], [0.518, 0], [0, -0.518], [-0.518, 0]], "o": [[0.518, 0], [0, -0.518], [-0.518, 0], [0, 0.518], [0, 0]], "v": [[52.5, 13.104], [53.438, 12.166], [52.5, 11.229], [51.562, 12.166], [52.5, 13.104]]}, "a": 0}}, {"ty": "fl", "o": {"k": 100, "a": 0}, "c": {"k": [0.298, 0.141, 0.114, 1], "a": 0}}, {"ty": "tr", "s": {"k": [100, 100], "a": 0}, "o": {"k": 100, "a": 0}}]}, {"ty": "gr", "it": [{"ty": "sh", "d": 1, "ks": {"k": {"c": true, "i": [[0, 0], [0, 11.132], [11.132, 0], [0, -11.132], [-11.132, 0]], "o": [[11.132, 0], [0, -11.132], [-11.132, 0], [0, 11.132], [0, 0]], "v": [[22.969, 45.916], [43.125, 25.76], [22.969, 5.604], [2.812, 25.76], [22.969, 45.916]]}, "a": 0}}, {"ty": "fl", "o": {"k": 100, "a": 0}, "c": {"k": [1, 0.898, 0.824, 1], "a": 0}}, {"ty": "tr", "s": {"k": [100, 100], "a": 0}, "o": {"k": 100, "a": 0}}]}]}], "v": "5.5.2", "fr": 60, "ip": 0, "op": 60, "w": 60, "h": 61, "ddd": 0, "assets": []}